tradingpatterns/__init__.py
tradingpatterns/hard_data.py
tradingpatterns/tradingpatterns.py
tradingpattern-0.0.2.dist-info/LICENSE.md
tradingpattern-0.0.2.dist-info/METADATA
tradingpattern-0.0.2.dist-info/WHEEL
tradingpattern-0.0.2.dist-info/RECORD
