Metadata-Version: 2.1
Name: tradingpattern
Version: 0.0.2
Summary: Trading Pattern Scanner Identifies complex patterns like head and shoulder, wedge and many more.
Home-page: https://github.com/white07S/TradingPatternScanner
License: CC BY-NC-SA 4.0
Author: Preetam Sharma
Requires-Python: >=3.10,<4.0
Classifier: License :: Other/Proprietary License
Classifier: Programming Language :: Python :: 3
Classifier: Programming Language :: Python :: 3.10
Classifier: Programming Language :: Python :: 3.11
Requires-Dist: numpy (>=1.24.2,<2.0.0)
Requires-Dist: pandas (>=2.0.0,<3.0.0)
Project-URL: Repository, https://github.com/white07S/TradingPatternScanner
